dblog/__init__.py
dblog/admin.py
dblog/apps.py
dblog/handlers.py
dblog/models.py
django_dblog-0.3.0.dist-info/LICENSE
django_dblog-0.3.0.dist-info/METADATA
django_dblog-0.3.0.dist-info/WHEEL
django_dblog-0.3.0.dist-info/top_level.txt
django_dblog-0.3.0.dist-info/RECORD
