Metadata-Version: 2.1
Name: django-dblog
Version: 0.3.0
Summary: Django Database Logs
Home-page: https://grantjenks.com/docs/django-dblog/
Author: Grant Jenks
Author-email: contact@grantjenks.com
License: Apache 2.0
Project-URL: Documentation, https://grantjenks.com/docs/django-dblog/
Project-URL: Funding, https://gum.co/django-dblog
Project-URL: Source, https://github.com/grantjenks/django-dblog
Project-URL: Tracker, https://github.com/grantjenks/django-dblog/issues
Platform: UNKNOWN
Classifier: Development Status :: 4 - Beta
Classifier: Intended Audience :: Developers
Classifier: License :: OSI Approved :: Apache Software License
Classifier: Natural Language :: English
Classifier: Programming Language :: Python
Classifier: Programming Language :: Python :: 3
Requires-Python: >=3
License-File: LICENSE
Requires-Dist: Django
